{
    "id": "_u_sanityismyvanity",
    "name": "\/u\/sanityismyvanity",
    "accent_background": "#865FC5",
    "accent_color": "white",
    "author": "-",
    "cards": [
        {
            "id": "w_f1f38e7e9761e00af7481e27fe64c6e07776f756",
            "content": {
                "en": "69'ing a 96 year old."
            }
        },
        {
            "id": "w_d484a91f5eb8534af03aaf4f2c32e01ad9780ca0",
            "content": {
                "en": "A baby cage."
            }
        },
        {
            "id": "w_5c5bc45d990f54f52dedd245c657437f2ec5981e",
            "content": {
                "en": "A bag of hammered assholes."
            }
        },
        {
            "id": "w_09caed77e327916b8b54b23e1f3f417ed58c597c",
            "content": {
                "en": "A box stuffed with gay porn."
            }
        },
        {
            "id": "w_e87ac00be754bf02b1422b5ebfd6146db5bbf348",
            "content": {
                "en": "A burlesque performer named Phyllis."
            }
        },
        {
            "id": "w_ef0bc976af4b8748d04e455705a4bba268377973",
            "content": {
                "en": "A C-section catastrophe."
            }
        },
        {
            "id": "w_aa7f6a6be2f9459764487cdd202a9de83e4f7531",
            "content": {
                "en": "A case of the Mondays."
            }
        },
        {
            "id": "w_0b1856c09f9d2325fa0a539fea09c8ca4bafe7b5",
            "content": {
                "en": "A clit that&apos;s just too big."
            }
        },
        {
            "id": "w_c07a1452e781be546dfc87b02e4334531ed7439d",
            "content": {
                "en": "A clubfooted hunchback."
            }
        },
        {
            "id": "w_8e53a2c1245bcbaa0c24722043fc7b30c5fc1301",
            "content": {
                "en": "A coffee enema."
            }
        },
        {
            "id": "w_b9a360fb8ccf5c9cbe683b1ef8ed822d2879cd8e",
            "content": {
                "en": "A couple of GILFs, ass-to-ass."
            }
        },
        {
            "id": "w_14e7094b4bcebeee75a95d385e8154e2c4cda9a0",
            "content": {
                "en": "A denim thong."
            }
        },
        {
            "id": "w_d02efec9daed16587beb038bffcd0d6b8f266232",
            "content": {
                "en": "A do-it-yourself vasectomy kit."
            }
        },
        {
            "id": "w_b34a2bea9f0db35d9ccefeed049764a1be98552a",
            "content": {
                "en": "A freshly shorn scrotum."
            }
        },
        {
            "id": "w_dafe7cab9ac0ef803493b670f8710c7e56aeebcd",
            "content": {
                "en": "A Funyun cock ring."
            }
        },
        {
            "id": "w_ce6a06d617959dae7d94d9c3346ad38e807102df",
            "content": {
                "en": "A gigantic, uncontrollable whirling death machine."
            }
        },
        {
            "id": "w_63c656e44b65081de4e648e9e3139901f75ea534",
            "content": {
                "en": "A good old fashioned skullfucking."
            }
        },
        {
            "id": "w_623974475d79333d9f3bc1c9d34ad1c1d06182bc",
            "content": {
                "en": "A great disturbance in the Force."
            }
        },
        {
            "id": "w_c54c3117ec79c19a7be37d1cf439a3f7ea10d92a",
            "content": {
                "en": "A high level of beaver activity."
            }
        },
        {
            "id": "w_907860564a1de4ebd93432b1ff06f8e0796ab6f6",
            "content": {
                "en": "A hockey luvin homo."
            }
        },
        {
            "id": "w_482acdcd4df8cfbfedb4b49f26c6791ce07f2842",
            "content": {
                "en": "A horse with a microcock."
            }
        },
        {
            "id": "w_6f9b9d2c33c8fd407af59f2208bac03d26ba5a88",
            "content": {
                "en": "A jigger of semen."
            }
        },
        {
            "id": "w_dafa188f6c24f649b20a9ef549c982fd9121b721",
            "content": {
                "en": "A lubricated goat."
            }
        },
        {
            "id": "w_1eb171e544af7cc615e93ee60a70677106f330cc",
            "content": {
                "en": "A meat popsicle."
            }
        },
        {
            "id": "w_b1ae77fbac4a67af5180561ac280186ae0aee444",
            "content": {
                "en": "A melon baller."
            }
        },
        {
            "id": "w_843326409198d0479b7194a6185e1cca1a33ded9",
            "content": {
                "en": "A menstrual cyclone."
            }
        },
        {
            "id": "w_1e00dcdc172c7357d02a7a96c16d9ac027020705",
            "content": {
                "en": "A moldy rectum."
            }
        },
        {
            "id": "w_cedd6b9ddc30975d0504652d566892160ca8be14",
            "content": {
                "en": "A mouth for hire."
            }
        },
        {
            "id": "w_0bd860d5607c7bdad4d952d76989cba358f8faa3",
            "content": {
                "en": "A nightmare involving a deli slicer."
            }
        },
        {
            "id": "w_0b3bc2c70a53e4dba0cfd235963eae062cc0ef02",
            "content": {
                "en": "A phantom limb."
            }
        },
        {
            "id": "w_e887fd5ae9919b08b0473652527310d0e918294a",
            "content": {
                "en": "A playground fire."
            }
        },
        {
            "id": "w_4044e030d8be7bcbf441251c9b6b1b1c3b3799d1",
            "content": {
                "en": "A prolapsed anus."
            }
        },
        {
            "id": "w_5d0d009e3e1b5883b4ae4e0e17a03769a155594c",
            "content": {
                "en": "A pudgy gay man with a comb over."
            }
        },
        {
            "id": "w_3ccf6fd11422297cf7926f183ab2716b0d35b054",
            "content": {
                "en": "A puffy vadge."
            }
        },
        {
            "id": "w_b26c441dc60794e3333b5de1ce0f3fb359e07cbd",
            "content": {
                "en": "A rape van."
            }
        },
        {
            "id": "w_995364b845820e7cadd04fcf33f25f79ecb897a8",
            "content": {
                "en": "A remarkably convincing argument for slavery."
            }
        },
        {
            "id": "w_ab0bca3dafaeca9a240e0d43099dfe83c77a9647",
            "content": {
                "en": "A sexy sasquatch."
            }
        },
        {
            "id": "w_40d3d048e6c0ab57fa522622b50428383c6f30d0",
            "content": {
                "en": "A singing vagina."
            }
        },
        {
            "id": "w_78f172493b1d104e8fe2425c4b85691e4dff5d3c",
            "content": {
                "en": "A skidmark the size of a Steak-umm."
            }
        },
        {
            "id": "w_bc10d392775fde874a0bfe71eb44d83a4e63e6f6",
            "content": {
                "en": "A slideshow of abnormal genitalia."
            }
        },
        {
            "id": "w_cc8ca3ad15b5ade373c67299b5a298ae3d14dc31",
            "content": {
                "en": "A sorority row murder spree."
            }
        },
        {
            "id": "w_240401807600f7c3aa289b8b47f8cca88391684f",
            "content": {
                "en": "A strap-on love missile."
            }
        },
        {
            "id": "w_bf1bd0fa4ae3ecbdfe0decd93c44f0065c597df7",
            "content": {
                "en": "A sucking chest wound."
            }
        },
        {
            "id": "w_cfa02062d5e65a2a739c5de3f1fc275cd762627e",
            "content": {
                "en": "A test tube baby shooter."
            }
        },
        {
            "id": "w_4ff77aa880c89da1861054f2d5cc7b22d633c864",
            "content": {
                "en": "A touching moment between a wealthy old woman and her Mexican gardener."
            }
        },
        {
            "id": "w_633267165217c0d888e3491eda42ee229538b51a",
            "content": {
                "en": "A tragically mannish drag queen."
            }
        },
        {
            "id": "w_26ccbed136862dda9878bc63750070c239630a38",
            "content": {
                "en": "A Transylvanian teabag."
            }
        },
        {
            "id": "w_154f5c57582ade8242c55ef1ae57d58dde11bfe6",
            "content": {
                "en": "A Turkish bath."
            }
        },
        {
            "id": "w_6fc3927217b75fc72e78ebf873c4ea8820ec15dc",
            "content": {
                "en": "A vending machine filled with soiled panties."
            }
        },
        {
            "id": "w_1e073bca9792307709c77cd631081895f61dbb47",
            "content": {
                "en": "A very admirable cumfart."
            }
        },
        {
            "id": "w_8aff3391f3c55cc643d898c2ef15f68cd8b35e93",
            "content": {
                "en": "ABBA."
            }
        },
        {
            "id": "w_5277de78cd2749ab27ff588f3b756369b598dda6",
            "content": {
                "en": "Aggressive nipple play."
            }
        },
        {
            "id": "w_234b1a8c674809f444715e554e352b7cde130b0c",
            "content": {
                "en": "An abortion survivor."
            }
        },
        {
            "id": "w_827f3339d804afb710c8d8bfffbe06813f1f6d95",
            "content": {
                "en": "An anorexic tween."
            }
        },
        {
            "id": "w_6acc113714dbf8a4e10238baafd9355f30d9f49f",
            "content": {
                "en": "An engorged member."
            }
        },
        {
            "id": "w_df3f4240335b3099d7e64963467444f4e63b3c7d",
            "content": {
                "en": "An erotic dream featuring Pat Robertson."
            }
        },
        {
            "id": "w_e569d027683c8ff01d03dd46f71c5ebfc67faeca",
            "content": {
                "en": "An overdose of Cialis."
            }
        },
        {
            "id": "w_2449d14e52c5c0e0ccd483c10c1d8e32e2df144c",
            "content": {
                "en": "An umbilical scab."
            }
        },
        {
            "id": "w_0ea64c69424cfa3bfbe265a089eb50fe7453657b",
            "content": {
                "en": "Anal leakage."
            }
        },
        {
            "id": "w_c27aad4c46db05a193a6b6b126845c7ad9d978be",
            "content": {
                "en": "Another goddamn virus from surfing questionable porn."
            }
        },
        {
            "id": "w_199926083b9fb21c6ffeb206bc7c6b68c7793a02",
            "content": {
                "en": "Antibiotic-resistant gonorrhea."
            }
        },
        {
            "id": "w_7e58191a82bdfb9b7240cd49b3a70166bca4d435",
            "content": {
                "en": "Antidisestablishmentarianism."
            }
        },
        {
            "id": "w_666ba63af76a6a19b5f5038782f2afa37ae46791",
            "content": {
                "en": "Antipsychotics."
            }
        },
        {
            "id": "w_4926a3683922671d8f7fcdccab223ae6c4d2e6e0",
            "content": {
                "en": "Arterial spray."
            }
        },
        {
            "id": "w_a9bfde33853c495722ee25c237b8fc561d6c6a7d",
            "content": {
                "en": "Attorney-client privilege."
            }
        },
        {
            "id": "w_cebe8b7b708d3a05f8a8f928e69a86fcef89f3fe",
            "content": {
                "en": "Barbed wire marital aids."
            }
        },
        {
            "id": "w_2d181e6e5f665a143b7edf8e3fbce3bcc3701628",
            "content": {
                "en": "Beardsley McTurbanhead."
            }
        },
        {
            "id": "w_58f3cb453d6ddac95d1694f8fba4ecafd8179891",
            "content": {
                "en": "Beastiality Anonymous."
            }
        },
        {
            "id": "w_c22b025672a8e953e498372ad50a5c008477a933",
            "content": {
                "en": "Being hypnotized by dem titties!"
            }
        },
        {
            "id": "w_60c17b3c5bfc3c96d81402d6ebc0a2dff1119fc4",
            "content": {
                "en": "Bingo night at the Church of Satan."
            }
        },
        {
            "id": "w_d541f7804e2b8c6c5acf52ed2f69e888360e9479",
            "content": {
                "en": "Bloody discharge."
            }
        },
        {
            "id": "w_ecacebd0751e70278a43ca9428871db98c5fd817",
            "content": {
                "en": "Bono, the twat."
            }
        },
        {
            "id": "w_bfdc5b979b23e14aa3d37c6870d5ea27726c6ab3",
            "content": {
                "en": "Bringing a colostomy bag to a water balloon fight."
            }
        },
        {
            "id": "w_f9c96cd68082fac384fa486528ea9f77ef7b450d",
            "content": {
                "en": "Bumming out hippies by explaining to them 4\/20 was Hitler&apos;s birthday."
            }
        },
        {
            "id": "w_3d950032dd5d5df8434e686eec4d500ea6013b63",
            "content": {
                "en": "Cajuns."
            }
        },
        {
            "id": "w_0921b4b23f24891cae8d2f3f9306911417e1880b",
            "content": {
                "en": "Cataclysmic failure."
            }
        },
        {
            "id": "w_ec65a2bec934cc417d0903880cbf425e7529087a",
            "content": {
                "en": "Charles Manson&apos;s intoxicating stare."
            }
        },
        {
            "id": "w_69e36bbd2e0392398312afbd5078f4c03be12ac2",
            "content": {
                "en": "CHICKENFUCKER!"
            }
        },
        {
            "id": "w_9134a8dcff842aa33d299557b407e6477077e545",
            "content": {
                "en": "Children&apos;s Television Workshop."
            }
        },
        {
            "id": "w_957927b47672aa77d5468105b40bab1fe4031592",
            "content": {
                "en": "Chum."
            }
        },
        {
            "id": "w_b402f91467318597a25450a0bc8a3b1a924d4a89",
            "content": {
                "en": "Climate change deniers."
            }
        },
        {
            "id": "w_bfba49584d53c5c3f9d8f6cb9d2716f63aecd1e7",
            "content": {
                "en": "Cluttering up her butter gutter."
            }
        },
        {
            "id": "w_e7d37b911e53d58ce06af4297e82d01ffb8a56b3",
            "content": {
                "en": "Cockgobblers."
            }
        },
        {
            "id": "w_71816d7bb23485942998c219998353dbe8b687d7",
            "content": {
                "en": "Cold, dead eyes."
            }
        },
        {
            "id": "w_7f56f8a918e90c816c9926dcbcb833659ea1ad44",
            "content": {
                "en": "Coprophilia."
            }
        },
        {
            "id": "w_8fb468f00acf9360b7db0f25cfde380e66a04dbe",
            "content": {
                "en": "Crotch rot."
            }
        },
        {
            "id": "w_2de6d90e93e83ac15e37285b4b336763b9e842b0",
            "content": {
                "en": "Cultivating an epic unibrow."
            }
        },
        {
            "id": "w_6a143fa68ab93371d95031c0d0f85b83c217ee09",
            "content": {
                "en": "Cum that&apos;s simply not the right color or consistency."
            }
        },
        {
            "id": "w_c61456be0e204644fba93f749a525136009e47b9",
            "content": {
                "en": "Cunt muffins."
            }
        },
        {
            "id": "w_44af1e462f5dcfbf0752670d73038bb9037823b0",
            "content": {
                "en": "Dainbramage."
            }
        },
        {
            "id": "w_1033d175e1b8c7db5966a148a0d0e1ad59df6cac",
            "content": {
                "en": "Dandruff as pure as the driven snow."
            }
        },
        {
            "id": "w_baee3ffd8a9b8162c95bc3dd82e1b77c57c80aa0",
            "content": {
                "en": "Death by RoboCop."
            }
        },
        {
            "id": "w_b25ce09ef48f27c7f9209c9a92c0245d48a4f97b",
            "content": {
                "en": "Declaring a jihad."
            }
        },
        {
            "id": "w_0e9a45bd840e1ce58c4975d995a6891c1547cadc",
            "content": {
                "en": "Detachable penis."
            }
        },
        {
            "id": "w_715ea223d2431ee28141980938fc9d5c77d3a017",
            "content": {
                "en": "Dick jokes."
            }
        },
        {
            "id": "w_bfbabff265a202f8fc9c28b35773abb1de50d710",
            "content": {
                "en": "Diplomatic immunity."
            }
        },
        {
            "id": "w_8d08dda7dae3f68e6cf79451bd8f99d83c87297a",
            "content": {
                "en": "Dipping your balls in it."
            }
        },
        {
            "id": "w_004be229693c01758a000576b7c27284e71aa632",
            "content": {
                "en": "Double vaginal double anal."
            }
        },
        {
            "id": "w_7a159964a71fc320fa36c59d40cf93ae409add3d",
            "content": {
                "en": "Drowning in hamster spunk."
            }
        },
        {
            "id": "w_d83e2a9e07b4290aa0db002a8efc6ad1ccf0e6ef",
            "content": {
                "en": "Drunk on cock."
            }
        },
        {
            "id": "w_e2b8adf1d7ba7f85f91fcc921f5b1642e83c2020",
            "content": {
                "en": "Duck faced bitches."
            }
        },
        {
            "id": "w_e12d733a665503c36b89eb3a4941384df3353102",
            "content": {
                "en": "Dueling banjos."
            }
        },
        {
            "id": "w_f06479841d0b2c086bbe30ff630811cd0f3ec5c5",
            "content": {
                "en": "Dumpster sex."
            }
        },
        {
            "id": "w_87737127a0f58a9faaecedd782e68ce1bf4fbb7e",
            "content": {
                "en": "Euthanising the unwanted pet population for fun and profit."
            }
        },
        {
            "id": "w_6524af600deb724698e6fba3377ef221bb90caf0",
            "content": {
                "en": "Feeling like MacGyver because you turned a Ziploc bag and a rubber band into a makeshift condom."
            }
        },
        {
            "id": "w_b3e662f1e477705083a34109157b723132578103",
            "content": {
                "en": "Flied lice."
            }
        },
        {
            "id": "w_b70cce66d6b7be966e614c2df1fc18fb3711220e",
            "content": {
                "en": "Frankenpenis."
            }
        },
        {
            "id": "w_22c8f5f6cc1f945dae215178281f8e639a948392",
            "content": {
                "en": "Free mustache rides."
            }
        },
        {
            "id": "w_8647bd1ee18004023be35538ca49a49b61f88284",
            "content": {
                "en": "Fudgie the Whale and Cookie Puss."
            }
        },
        {
            "id": "w_45af6ae2a6187cae8b1f8c074688bceb3895ddc7",
            "content": {
                "en": "Gamey liver."
            }
        },
        {
            "id": "w_fba5b2535981782450cdef190e3b52e4244222aa",
            "content": {
                "en": "Gangbanging a corpse."
            }
        },
        {
            "id": "w_f03eb76e4727ef1bb5898fc7e767f6b603e7123a",
            "content": {
                "en": "Gaping anal."
            }
        },
        {
            "id": "w_45a32247fb198f84fc86f93e8bb835a33f0f9fce",
            "content": {
                "en": "George Takei."
            }
        },
        {
            "id": "w_53de5ab5011c9cb172cff9bcb5a389a386b26af9",
            "content": {
                "en": "Gerbilling."
            }
        },
        {
            "id": "w_0afa6738d5dbbc783ba86d8928571fa81e464ffd",
            "content": {
                "en": "Geriatric enema party!"
            }
        },
        {
            "id": "w_96ef1b45d766da1c9d283f12c9b665e093b9b8a3",
            "content": {
                "en": "Getting a box full of razor blades and sleeping pills from your Secret Santa."
            }
        },
        {
            "id": "w_57b72a38dadccc627ebbd4f2edc6cb2e95e12068",
            "content": {
                "en": "Getting chased by a gang of homicidal, time traveling children from a post-apocalyptic future."
            }
        },
        {
            "id": "w_95030729b253d9ef4f95093173202fb40dfbd2ff",
            "content": {
                "en": "Getting fucked up on PCP and violently masturbating to photos of Marty Feldman."
            }
        },
        {
            "id": "w_855199639e5df45a100c1146a2cc1f6b5fe8faf3",
            "content": {
                "en": "Getting paid in cocaine and unicorns."
            }
        },
        {
            "id": "w_14fbfa4a050df5fc4b8ed67cfddb20bb3574b1ef",
            "content": {
                "en": "Getting photobombed by Bill Murray."
            }
        },
        {
            "id": "w_69d419f951d91f0d1ee51ece851a7a77d6cdca53",
            "content": {
                "en": "Getting sexy with her cul-de-sac."
            }
        },
        {
            "id": "w_7b8d7d1a68e345bb735949d2d67d78e481834ac7",
            "content": {
                "en": "Getting shanked for a box of Newports."
            }
        },
        {
            "id": "w_9b12f0a3edc7f689b1471e499e83e3e60b71e0e2",
            "content": {
                "en": "Going balls deep."
            }
        },
        {
            "id": "w_fbc776945431850186724c71518772161902a89e",
            "content": {
                "en": "Going gay for God."
            }
        },
        {
            "id": "w_3426fff02954a0aa907c8be8cec345b49086efe4",
            "content": {
                "en": "Gold chains overlaying a copious amount of chest hair."
            }
        },
        {
            "id": "w_40176942919a04348e17e07c3f8bd182b3d752f4",
            "content": {
                "en": "Gore. Buckets and buckets of gore."
            }
        },
        {
            "id": "w_afbe6c2bcc0ef922be7d46b5db9851b6c9656439",
            "content": {
                "en": "Grandma&apos;s cameltoe."
            }
        },
        {
            "id": "w_47ee843636c1a3c7b84aec14b7b0ed6dbb81ea68",
            "content": {
                "en": "Gun porn."
            }
        },
        {
            "id": "w_4a7ee6ac9647ccd790193c6bb082998238b95cc2",
            "content": {
                "en": "Ham on the bone."
            }
        },
        {
            "id": "w_59004404e0c5a59ca6b91e6164e76d30ddcfc2ac",
            "content": {
                "en": "Hamburger Helper."
            }
        },
        {
            "id": "w_b5b040c329350e33290cae6613eea20ce5895431",
            "content": {
                "en": "Herve Villechaize dressed up as a little Hitler."
            }
        },
        {
            "id": "w_98b6d4466d1ceb8b53c8345655c1ad94a2a30f53",
            "content": {
                "en": "Hilary Swank&apos;s shattered teeth littering the street."
            }
        },
        {
            "id": "w_dffe07c3b279201839b9bc52dc72c47fee88d7ad",
            "content": {
                "en": "Hitler Youth Easy Bake Ovens."
            }
        },
        {
            "id": "w_418513a35befb541931727aec7170de7bf412e6c",
            "content": {
                "en": "Hitlerotica."
            }
        },
        {
            "id": "w_1f24c4c3d716f3b11fdda9c7f2c65968d23599fa",
            "content": {
                "en": "Inhumane medical experiments."
            }
        },
        {
            "id": "w_5f3280aac465d7f23f8f844043b05827d0439b46",
            "content": {
                "en": "Intestinal distress."
            }
        },
        {
            "id": "w_ab911fe02f195aa3ae4e42ea3c99f81cef5d197b",
            "content": {
                "en": "Jerkin' it with Jergens."
            }
        },
        {
            "id": "w_ff38903bb3938cdd351a476a24d4b2e3952d0588",
            "content": {
                "en": "Jews for Jesus."
            }
        },
        {
            "id": "w_21f59c7a3ffed08ec041c0a169aa216722f412e7",
            "content": {
                "en": "Keeping a chainsaw next to your bed. You know, just in case."
            }
        },
        {
            "id": "w_0297afbce502dc23f1f678568d4d40290b2300f5",
            "content": {
                "en": "Kitten fisting."
            }
        },
        {
            "id": "w_f8231ddda54570ff605eb6643ef96ab2a9ee6550",
            "content": {
                "en": "Kitten mittens."
            }
        },
        {
            "id": "w_4e24f65025d82c043d285bc9cd5543b9ea1f0d44",
            "content": {
                "en": "Kung Fu Grip."
            }
        },
        {
            "id": "w_7c508ddb30fadd13c2874567e74bce6ac41778f5",
            "content": {
                "en": "L. Ron Hubbard."
            }
        },
        {
            "id": "w_296f46e261642123014b3ffb9bfb5d995676edad",
            "content": {
                "en": "Lording over your inferiors."
            }
        },
        {
            "id": "w_c219f15755503b9aea7fe5bf6c1690824e4ed827",
            "content": {
                "en": "Mandingo fighting."
            }
        },
        {
            "id": "w_0b4c9b2dd0b252f46dccb8a2604b275764da1199",
            "content": {
                "en": "Meat Loaf eating meatloaf."
            }
        },
        {
            "id": "w_454c5a6ec3d87408d761caf674d1586fff7db326",
            "content": {
                "en": "Mondo sexual perversion."
            }
        },
        {
            "id": "w_8aab702b7e473684eb61d600c5f1d9b6075dd75d",
            "content": {
                "en": "More dead nuns than you can shake a stick at."
            }
        },
        {
            "id": "w_01b457bd1d9dd91ca3ddd18091ac53c6d3c97168",
            "content": {
                "en": "Mr. T fisting kittens."
            }
        },
        {
            "id": "w_642966d754e1b1ce8ed8fecb6bae67b602b74dfa",
            "content": {
                "en": "Mrs. Claus, blindfolded and begging for cock."
            }
        },
        {
            "id": "w_8bce7e1bf6c27b080acf2b3ed96bedf71e0908a4",
            "content": {
                "en": "Neil Diamond&apos;s cock."
            }
        },
        {
            "id": "w_c2f10aa113a1a6d943f5b3970ce41b9d2af7f520",
            "content": {
                "en": "Nuns with guns."
            }
        },
        {
            "id": "w_9ae220aa9d0ccad84e509de73100603a6fafc3ba",
            "content": {
                "en": "Offhand racist remarks."
            }
        },
        {
            "id": "w_fa7f583bf22908f62b89f52f6a90193ff863198c",
            "content": {
                "en": "One withered tit."
            }
        },
        {
            "id": "w_ea4f5d5051eef94a23183bfee12911689a3752aa",
            "content": {
                "en": "Pedos in Speedos."
            }
        },
        {
            "id": "w_79c2706d4704a4b176873f0a2eb8a4622d70a57b",
            "content": {
                "en": "Penis origami."
            }
        },
        {
            "id": "w_5991c40a1e8ad67f25f155cde5b17c97a9895412",
            "content": {
                "en": "Performing fellatio on a geoduck."
            }
        },
        {
            "id": "w_0baef76a362462c0199cf314bea520d378c61287",
            "content": {
                "en": "PooTrap Magic Poop Collector! No poops! No oops!"
            }
        },
        {
            "id": "w_f6d6c68c0cfce35315c26adb5d1b9fe247583420",
            "content": {
                "en": "Pope on a rope."
            }
        },
        {
            "id": "w_af1bbbcc750a7a5013d564fedbc6137b961933c0",
            "content": {
                "en": "Punky Brewster."
            }
        },
        {
            "id": "w_b6ceae66ae3b41213c381e4412c5ed4435ec6d2a",
            "content": {
                "en": "Puppy dog eyes."
            }
        },
        {
            "id": "w_c43faa89b567e6cf2cde78388cdaa85ed6ba03d5",
            "content": {
                "en": "Queef Latina."
            }
        },
        {
            "id": "w_981711c29a33e05420a70621bec5b1c993ba3c9f",
            "content": {
                "en": "Rapeman."
            }
        },
        {
            "id": "w_4a7274b6e55fe4fc422fd468a0532fbec229ac9e",
            "content": {
                "en": "Reeking of ocelot piss."
            }
        },
        {
            "id": "w_9b54b898de3ed02476de8e66e8585e2dfbbbafa8",
            "content": {
                "en": "Retard strength."
            }
        },
        {
            "id": "w_ffc73c2d30d3d8b5e8bf8713a197d47b7ff36c12",
            "content": {
                "en": "Roast placenta."
            }
        },
        {
            "id": "w_5bcf20205728f5ec296904182727eaa4f65a0cd2",
            "content": {
                "en": "Ronald McDonald, wearing only a pair of red nugget smugglers, seductively pulling down one side to expose his pubic mound of fries."
            }
        },
        {
            "id": "w_f083611362832c2b412729efc7b8930ece6f0d6f",
            "content": {
                "en": "Sarcastically praising Allah."
            }
        },
        {
            "id": "w_608169d689d021495c99c1ea6d245f6b500ab933",
            "content": {
                "en": "Saved by the Bell: The College Years."
            }
        },
        {
            "id": "w_f97f6baf9e2959e6c0573da4554a6ebbd74c0cb9",
            "content": {
                "en": "Scabby pickles."
            }
        },
        {
            "id": "w_de643c72747f109527be7326ddbd26f639755963",
            "content": {
                "en": "Self-immolation protest s'mores."
            }
        },
        {
            "id": "w_2c33e6cb6d6fb728a6cdc6b69cc1c1a7c191ce93",
            "content": {
                "en": "Serial murder."
            }
        },
        {
            "id": "w_666d2c9d88eb24a83c361c157474824d12f5eba8",
            "content": {
                "en": "Setting fire to a mime."
            }
        },
        {
            "id": "w_f9ee7d104e3c561363b2533e47c947b089b81124",
            "content": {
                "en": "Setting your phaser to fabulous!"
            }
        },
        {
            "id": "w_f96e14331e17367fe32dcf5e0541283c1b628e09",
            "content": {
                "en": "Sex Dwarf."
            }
        },
        {
            "id": "w_e5feeafcd23160706b5306924dad402ca22aaea2",
            "content": {
                "en": "Sexecution."
            }
        },
        {
            "id": "w_9db95f85772835403152e701e7d1affe3fed50c2",
            "content": {
                "en": "Shitting out a small watermelon."
            }
        },
        {
            "id": "w_ca657985e78745be2335b1ea93d5af699a5abca2",
            "content": {
                "en": "Shitting yourself at an inopportune moment."
            }
        },
        {
            "id": "w_580dc0b858022d87e8df53aad9383600697abbfa",
            "content": {
                "en": "Sneaking into the back kitchen at TGI Friday&apos;s and microwaving a full diaper."
            }
        },
        {
            "id": "w_e2437f4bce7431123d9b03bc28a8059927a4fdd8",
            "content": {
                "en": "So much vaginal discharge."
            }
        },
        {
            "id": "w_23c6ca9c2afbbdf6ca74d2091e227e8da2642f35",
            "content": {
                "en": "Socially acceptable rape."
            }
        },
        {
            "id": "w_6f98740d9a23f7f6370d410dbb6b189b02a761bd",
            "content": {
                "en": "Some fava beans and a nice chianti."
            }
        },
        {
            "id": "w_14195461ccab1861f1bbef155ba03cdd8e44cf44",
            "content": {
                "en": "Sparkles and glitter."
            }
        },
        {
            "id": "w_655d112ea05d296d225ece3f9dd29268105cab7e",
            "content": {
                "en": "Spock teabagging Kirk after a Vulcan nerve pinch."
            }
        },
        {
            "id": "w_681b517e167e8dd578d35a43592d6bd68427e999",
            "content": {
                "en": "Squealing like a pig."
            }
        },
        {
            "id": "w_b85f2335380fb37ac38e23ab74d9b625568f0824",
            "content": {
                "en": "Sucking it."
            }
        },
        {
            "id": "w_56fabb0f47764d5c687157fde097a5123d804bb0",
            "content": {
                "en": "Sweep the leg."
            }
        },
        {
            "id": "w_bdd7f4faa574d5c1af5a19b590226e334d720f7d",
            "content": {
                "en": "Tasting the rainbow."
            }
        },
        {
            "id": "w_ff9a0586db56934d0f381447b1bc8f599652d1e6",
            "content": {
                "en": "Tea, Earl Grey, hot."
            }
        },
        {
            "id": "w_c61bbe0cee0be764ed0f72cb4d0db37a00c9e5bf",
            "content": {
                "en": "That fish that swims up your dick."
            }
        },
        {
            "id": "w_2d407e8a1125eb7ce86f7a417a0cd44f57ae8e4c",
            "content": {
                "en": "That which cannot be named."
            }
        },
        {
            "id": "w_2a82aa08d6dd5974220cff2ab906efa3ea439354",
            "content": {
                "en": "The 'Macho Man' Randy Savage"
            }
        },
        {
            "id": "w_8a1f3ba5c344755cbeb8a38fe3da364699613073",
            "content": {
                "en": "The Devil&apos;s butt boy."
            }
        },
        {
            "id": "w_7f9857e9ba51297241aaa7f7cb76b2b03bd4a1cc",
            "content": {
                "en": "The fevered hallucinations of a syphilitic mind."
            }
        },
        {
            "id": "w_b88ca1019783af7a75518c2a63fe6cf75a8b266a",
            "content": {
                "en": "The genital grinder."
            }
        },
        {
            "id": "w_ada7ed06d7099df58995810c9f804871f3c85d4d",
            "content": {
                "en": "The Holy Hand Grenade of Antioch."
            }
        },
        {
            "id": "w_6c9028bdd475ecd4822c0ecbc9b4c83a5759f747",
            "content": {
                "en": "The horrible, horrible things you would do if you actually owned a sex slave."
            }
        },
        {
            "id": "w_48bdbda46338e133cc3fc74eebb603601b9ecf7c",
            "content": {
                "en": "The Illuminati conspiracy."
            }
        },
        {
            "id": "w_79b08779b8adbcac6822bd8d61dfe1f6c97113ff",
            "content": {
                "en": "The liberal media machine."
            }
        },
        {
            "id": "w_4f3255e4937467548fa3048ad40c4ac662d86016",
            "content": {
                "en": "The Macarena."
            }
        },
        {
            "id": "w_4b78ffdb743fd010094729dd3d378bcf715c5b47",
            "content": {
                "en": "The mythical 4th hole."
            }
        },
        {
            "id": "w_b2b27a43c42718d77948468c8c829bc1cc812fac",
            "content": {
                "en": "The Pillsbury Doughboy blowing his load all over a toaster strudel."
            }
        },
        {
            "id": "w_8a05b6bb9d3d2f4604be0dd66e3f691c5d8832bd",
            "content": {
                "en": "The pooled blood of a Filipino cabana boy."
            }
        },
        {
            "id": "w_a74bd831acc87b071176822284b8d8cae4adc572",
            "content": {
                "en": "The quaint Austrian village of Fucking."
            }
        },
        {
            "id": "w_e264c2b3f49508639ce188a61e55a62f44a6af55",
            "content": {
                "en": "The regret that instantly follows paying $9.99 for pay-per-view porn."
            }
        },
        {
            "id": "w_5a2723798566e9c27937822b531efd6e63f0e9f7",
            "content": {
                "en": "The scent of virgin blood."
            }
        },
        {
            "id": "w_b04d93d92966df511c2d23a9a5cc2504015e5385",
            "content": {
                "en": "The soothing sounds of Kenny G."
            }
        },
        {
            "id": "w_4e6c42dbdb87926fcb0863206e372eecc5c4a043",
            "content": {
                "en": "The soulful mating cry of the hippopotamus."
            }
        },
        {
            "id": "w_f2091c843141a0242f45eb56d26b24fada936955",
            "content": {
                "en": "The squirts."
            }
        },
        {
            "id": "w_007bf4e28669b5fc3d8593774aaf7872e8fdd916",
            "content": {
                "en": "The sudden desire for tartar sauce when going down on your woman."
            }
        },
        {
            "id": "w_675c18c58add22bc3c3ef7e2553c3769ddabd078",
            "content": {
                "en": "The throbbing manhood about to violate my innocence."
            }
        },
        {
            "id": "w_c13e7ad457b82a2cf21c51dc9179afb9f1b26d67",
            "content": {
                "en": "This shit called love."
            }
        },
        {
            "id": "w_36f64349e5633288d2ace6b193c2e75f2be541a5",
            "content": {
                "en": "Those donut-things you sit on when you have hemorrhoids."
            }
        },
        {
            "id": "w_7ea340cec1fc757081c049f84f6e9243e8702788",
            "content": {
                "en": "Throwing trash at the feet of a crying Indian."
            }
        },
        {
            "id": "w_f78a0323e0a13b953c29e41f372d95d2f7c3facb",
            "content": {
                "en": "Thunderdome!"
            }
        },
        {
            "id": "w_33bed804c83ebad62f5a84308261fe46e81bf912",
            "content": {
                "en": "Tits the size of Ethiopia."
            }
        },
        {
            "id": "w_b0cbbeec03a1610e52056a507b4e720e12f179d5",
            "content": {
                "en": "To crush your enemies, see them driven before you, and to hear the lamentation of their women."
            }
        },
        {
            "id": "w_672071ae0c8dc4cbc6f59095d817e5fe34f1608f",
            "content": {
                "en": "Travelling to Thailand with no intention to engage in sexual deviancy."
            }
        },
        {
            "id": "w_973e8058ccb4ed71e1ea543c4a23c9330d017671",
            "content": {
                "en": "Tricking Alzheimer&apos;s sufferers into prostitution."
            }
        },
        {
            "id": "w_6d6c487dbb60d9daaf312abc86e7a7b5331da048",
            "content": {
                "en": "Trying to teach Intelligent Design with a straight face."
            }
        },
        {
            "id": "w_4570f7a3d7f383b5761d962228362fbe8481dbc1",
            "content": {
                "en": "Turd Ferguson."
            }
        },
        {
            "id": "w_887de81b230d3a890d143b0e195fcbe590afd41e",
            "content": {
                "en": "Uncut man-meat."
            }
        },
        {
            "id": "w_66395755405270dfa093770c0f180b1ed928f805",
            "content": {
                "en": "Unicornio, the Mexican unicorn."
            }
        },
        {
            "id": "w_b8d4407aa50c068e0e966a116e981826f1758340",
            "content": {
                "en": "Unintentional homoeroticism."
            }
        },
        {
            "id": "w_0c231d125186c99c4cd7722cab8d9a6417f99906",
            "content": {
                "en": "Using an infant to do your Shake Weight exercises."
            }
        },
        {
            "id": "w_7f8f9904f66985b09f13b2ece34246e2507f58fe",
            "content": {
                "en": "Using heroin, but only on the weekend."
            }
        },
        {
            "id": "w_446386835c18ab70797e2657bfb09f9c7f87756b",
            "content": {
                "en": "Vaccination induced autism."
            }
        },
        {
            "id": "w_f02d14c92b19958834eab2d0aae8a5e2c27e2a0a",
            "content": {
                "en": "Vladimir Putin, shirtless."
            }
        },
        {
            "id": "w_6773afdbc280f5d08e85b89673f1706d615faed4",
            "content": {
                "en": "Webelos."
            }
        },
        {
            "id": "w_76ea1f92730e9c94e661b428b6c5cb9844860665",
            "content": {
                "en": "What Gary Busey is thinking right now."
            }
        },
        {
            "id": "w_fd370e4c12fc7aac28adc1faea907aae24de4d56",
            "content": {
                "en": "White people problems."
            }
        },
        {
            "id": "w_a0306e36974c196e07f13a694e7acbf489641bee",
            "content": {
                "en": "Winking the brown eye."
            }
        },
        {
            "id": "w_efc337000d4f675d30e0d1c884a834d9b7b3f99f",
            "content": {
                "en": "X-rays of a girl passing gas."
            }
        },
        {
            "id": "w_081f481c4266e1916707bc186998624ea6fbdaed",
            "content": {
                "en": "Your big, knobbly, vibrating eggplant."
            }
        }
    ]
}